MANIFEST.in
README.md
TODO.md
aptly_api_cli.py
requirements.txt
setup.cfg
setup.py
Aptly_Api_Cli.egg-info/PKG-INFO
Aptly_Api_Cli.egg-info/SOURCES.txt
Aptly_Api_Cli.egg-info/dependency_links.txt
Aptly_Api_Cli.egg-info/pbr.json
Aptly_Api_Cli.egg-info/top_level.txt
aptly_cli/__init__.py
aptly_cli/aptly_api_requests.py
aptly_cli/cli/__init__.py
aptly_cli/cli/cli.py
debian/changelog
debian/compat
debian/control
debian/postinst
debian/rules