Metadata-Version: 1.0
Name: Aptly-Api-Cli
Version: 0.1
Summary: This python command line interface, executes calls to the Aptly server remotely, without blocking the Aptly database.
Home-page: https://github.com/TimSusa/aptly_api_cli
Author: Tim Susa
Author-email: timsusa@gmx.de
License: MIT
Keywords: aptly aptly-server debian
Platform: any
